LICENSE
README.md
setup.py
RAG_X/__init__.py
RAG_X/chunk_it.py
RAG_X/clean_it.py
RAG_X/extractor.py
RAG_X/get_evaluation_question.py
RAG_X/prag.py
RAG_X/trulens.py
RAG_X/utils.py
RAG_X_testing.egg-info/PKG-INFO
RAG_X_testing.egg-info/SOURCES.txt
RAG_X_testing.egg-info/dependency_links.txt
RAG_X_testing.egg-info/requires.txt
RAG_X_testing.egg-info/top_level.txt